Gym_env/__init__.py
Gym_env/envs/Gym_env.py
Gym_env/envs/__init__.py
Gym_env-0.0.2.dist-info/METADATA
Gym_env-0.0.2.dist-info/WHEEL
Gym_env-0.0.2.dist-info/top_level.txt
Gym_env-0.0.2.dist-info/RECORD
