Metadata-Version: 2.1
Name: Gym-env
Version: 0.0.2
Summary: A OpenAI Gym Env
Home-page: UNKNOWN
License: UNKNOWN
Platform: UNKNOWN
Requires-Dist: gym
